zh_mistake_text_aug/__init__.py
zh_mistake_text_aug/data_maker.py
zh_mistake_text_aug/data_model.py
zh_mistake_text_aug/exception.py
zh_mistake_text_aug/high_freq_zh_char.txt
zh_mistake_text_aug/utils.py
zh_mistake_text_aug-0.2.1.dist-info/WHEEL
zh_mistake_text_aug-0.2.1.dist-info/METADATA
zh_mistake_text_aug-0.2.1.dist-info/RECORD
