Metadata-Version: 2.1
Name: zh-mistake-text-aug
Version: 0.2.1
Summary: 中文錯誤類型文字增量
Home-page: https://github.com/p208p2002/zh-mistake-text-aug
Author: Philip Huang
Author-email: p208p2002@gmail.com
Requires-Python: >=3.8,<4.0
Classifier: Programming Language :: Python :: 3
Classifier: Programming Language :: Python :: 3.10
Classifier: Programming Language :: Python :: 3.8
Classifier: Programming Language :: Python :: 3.9
Requires-Dist: OpenCC (>=1.1.4,<2.0.0)
Requires-Dist: jieba (>=0.42.1,<0.43.0)
Requires-Dist: loguru (>=0.6.0,<0.7.0)
Requires-Dist: py-chinese-pronounce (>=0.1.5,<0.2.0)
Requires-Dist: pydantic (>=1.10.2,<2.0.0)
